struct4py/__init__.py
struct4py/struct.py
struct4py-1.0.0.dist-info/LICENSE
struct4py-1.0.0.dist-info/METADATA
struct4py-1.0.0.dist-info/WHEEL
struct4py-1.0.0.dist-info/RECORD
