Metadata-Version: 2.1
Name: struct4py
Version: 1.0.0
Summary: Matlab like structure for python, allowing for fast and easy indexing
Home-page: https://github.com/ahartlba/struct4py
License: MIT
Author: ahartlba
Author-email: you@example.com
Requires-Python: >=3.8.1,<4.0.0
Classifier: License :: OSI Approved :: MIT License
Classifier: Programming Language :: Python :: 3
Classifier: Programming Language :: Python :: 3.9
Classifier: Programming Language :: Python :: 3.10
Classifier: Programming Language :: Python :: 3.11
Classifier: Programming Language :: Python :: 3.12
